Workbook

Sheet Summary
A1: 90-Day Shelter-in-Place Tracker
A2: Estimates are approximate (late 2026). On Shopping List: change blue numbers (qty, prices); fill yellow cells (Status, Actual cost). Rows marked Have turn green.
A4: Phase | B4: Core low ($) | C4: Core high ($) | D4: Optional low ($) | E4: Optional high ($) | F4: All-in low ($) | G4: All-in high ($) | H4: Items | I4: Have | J4: Actual spent ($)
A5: 1 - This week | B5: =SUMIFS('Shopping List'!$H$2:$H$84,'Shopping List'!$A$2:$A$84,$A5,'Shopping List'!$J$2:$J$84,"N") -> 1243 | C5: =SUMIFS('Shopping List'!$I$2:$I$84,'Shopping List'!$A$2:$A$84,$A5,'Shopping List'!$J$2:$J$84,"N") -> 1983 | D5: =SUMIFS('Shopping List'!$H$2:$H$84,'Shopping List'!$A$2:$A$84,$A5,'Shopping List'!$J$2:$J$84,"Y") -> 0 | E5: =SUMIFS('Shopping List'!$I$2:$I$84,'Shopping List'!$A$2:$A$84,$A5,'Shopping List'!$J$2:$J$84,"Y") -> 0 | F5: =B5+D5 -> 1243 | G5: =C5+E5 -> 1983 | H5: =COUNTIFS('Shopping List'!$A$2:$A$84,$A5) -> 19 | I5: =COUNTIFS('Shopping List'!$A$2:$A$84,$A5,'Shopping List'!$K$2:$K$84,"Have") -> 0 | J5: =SUMIFS('Shopping List'!$L$2:$L$84,'Shopping List'!$A$2:$A$84,$A5) -> 0
A6: 2 - Within 2-4 weeks | B6: =SUMIFS('Shopping List'!$H$2:$H$84,'Shopping List'!$A$2:$A$84,$A6,'Shopping List'!$J$2:$J$84,"N") -> 3799 | C6: =SUMIFS('Shopping List'!$I$2:$I$84,'Shopping List'!$A$2:$A$84,$A6,'Shopping List'!$J$2:$J$84,"N") -> 6684 | D6: =SUMIFS('Shopping List'!$H$2:$H$84,'Shopping List'!$A$2:$A$84,$A6,'Shopping List'!$J$2:$J$84,"Y") -> 940 | E6: =SUMIFS('Shopping List'!$I$2:$I$84,'Shopping List'!$A$2:$A$84,$A6,'Shopping List'!$J$2:$J$84,"Y") -> 1720 | F6: =B6+D6 -> 4739 | G6: =C6+E6 -> 8404 | H6: =COUNTIFS('Shopping List'!$A$2:$A$84,$A6) -> 24 | I6: =COUNTIFS('Shopping List'!$A$2:$A$84,$A6,'Shopping List'!$K$2:$K$84,"Have") -> 0 | J6: =SUMIFS('Shopping List'!$L$2:$L$84,'Shopping List'!$A$2:$A$84,$A6) -> 0
A7: 3 - Within 60 days | B7: =SUMIFS('Shopping List'!$H$2:$H$84,'Shopping List'!$A$2:$A$84,$A7,'Shopping List'!$J$2:$J$84,"N") -> 2444 | C7: =SUMIFS('Shopping List'!$I$2:$I$84,'Shopping List'!$A$2:$A$84,$A7,'Shopping List'!$J$2:$J$84,"N") -> 4261 | D7: =SUMIFS('Shopping List'!$H$2:$H$84,'Shopping List'!$A$2:$A$84,$A7,'Shopping List'!$J$2:$J$84,"Y") -> 480 | E7: =SUMIFS('Shopping List'!$I$2:$I$84,'Shopping List'!$A$2:$A$84,$A7,'Shopping List'!$J$2:$J$84,"Y") -> 800 | F7: =B7+D7 -> 2924 | G7: =C7+E7 -> 5061 | H7: =COUNTIFS('Shopping List'!$A$2:$A$84,$A7) -> 40 | I7: =COUNTIFS('Shopping List'!$A$2:$A$84,$A7,'Shopping List'!$K$2:$K$84,"Have") -> 0 | J7: =SUMIFS('Shopping List'!$L$2:$L$84,'Shopping List'!$A$2:$A$84,$A7) -> 0
A8: TOTAL | B8: =SUM(B5:B7) -> 7486 | C8: =SUM(C5:C7) -> 12928 | D8: =SUM(D5:D7) -> 1420 | E8: =SUM(E5:E7) -> 2520 | F8: =SUM(F5:F7) -> 8906 | G8: =SUM(G5:G7) -> 15448 | H8: =SUM(H5:H7) -> 83 | I8: =SUM(I5:I7) -> 0 | J8: =SUM(J5:J7) -> 0
A10: Not budgeted: heating oil top-off, prescription copays, cash reserve (set aside, not spent).

Sheet Shopping List
A1: Phase | B1: Category | C1: Item | D1: Qty | E1: Unit | F1: Unit cost low ($) | G1: Unit cost high ($) | H1: Total low ($) | I1: Total high ($) | J1: Optional? | K1: Status | L1: Actual cost ($) | M1: Notes
A2: 1 - This week | B2: Heat & Power | C2: Battery CO alarms | D2: 4 | E2: each | F2: 25 | G2: 40 | H2: =D2*F2 -> 100 | I2: =D2*G2 -> 160 | J2: N | K2: Not bought | M2: Every level + outside sleeping areas
A3: 1 - This week | B3: Heat & Power | C3: ABC fire extinguisher | D3: 3 | E3: each | F3: 35 | G3: 60 | H3: =D3*F3 -> 105 | I3: =D3*G3 -> 180 | J3: N | K3: Not bought | M3: One per floor
A4: 1 - This week | B4: Heat & Power | C4: Indoor-rated propane heater (ODS + tip-over) | D4: 1 | E4: each | F4: 120 | G4: 180 | H4: =D4*F4 -> 120 | I4: =D4*G4 -> 180 | J4: N | K4: Not bought | M4: Awake use only, window cracked
A5: 1 - This week | B5: Heat & Power | C5: 1-lb propane cylinders | D5: 12 | E5: each | F5: 6 | G5: 9 | H5: =D5*F5 -> 72 | I5: =D5*G5 -> 108 | J5: N | K5: Not bought | M5: For the indoor heater
A6: 1 - This week | B6: Comms | C6: Hand-crank/solar NOAA weather radio (AM/FM) | D6: 1 | E6: each | F6: 40 | G6: 70 | H6: =D6*F6 -> 40 | I6: =D6*G6 -> 70 | J6: N | K6: Not bought
A7: 1 - This week | B7: Comms | C7: Battery AM/FM radio (backup) | D7: 1 | E7: each | F7: 20 | G7: 35 | H7: =D7*F7 -> 20 | I7: =D7*G7 -> 35 | J7: N | K7: Not bought
A8: 1 - This week | B8: Comms | C8: USB power banks | D8: 4 | E8: each | F8: 25 | G8: 40 | H8: =D8*F8 -> 100 | I8: =D8*G8 -> 160 | J8: N | K8: Not bought | M8: One per person
A9: 1 - This week | B9: Lighting | C9: LED lanterns | D9: 4 | E9: each | F9: 20 | G9: 35 | H9: =D9*F9 -> 80 | I9: =D9*G9 -> 140 | J9: N | K9: Not bought
A10: 1 - This week | B10: Lighting | C10: Headlamps | D10: 6 | E10: each | F10: 15 | G10: 25 | H10: =D10*F10 -> 90 | I10: =D10*G10 -> 150 | J10: N | K10: Not bought | M10: 1 per person + 2 spares
A11: 1 - This week | B11: Lighting | C11: Rechargeable AA/AAA set + USB charger | D11: 1 | E11: set | F11: 40 | G11: 60 | H11: =D11*F11 -> 40 | I11: =D11*G11 -> 60 | J11: N | K11: Not bought
A12: 1 - This week | B12: Lighting | C12: Alkaline AA (48) + AAA (24) | D12: 1 | E12: lot | F12: 30 | G12: 48 | H12: =D12*F12 -> 30 | I12: =D12*G12 -> 48 | J12: N | K12: Not bought
A13: 1 - This week | B13: Water | C13: Bottled water | D13: 60 | E13: gal | F13: 1 | G13: 1.5 | H13: =D13*F13 -> 60 | I13: =D13*G13 -> 90 | J13: N | K13: Not bought | M13: Covers first ~2 weeks
A14: 1 - This week | B14: Water | C14: Bathtub water bladders | D14: 2 | E14: each | F14: 30 | G14: 40 | H14: =D14*F14 -> 60 | I14: =D14*G14 -> 80 | J14: N | K14: Not bought | M14: ~100 gal each
A15: 1 - This week | B15: Food | C15: 2 weeks of no-cook food | D15: 1 | E15: lot | F15: 250 | G15: 400 | H15: =D15*F15 -> 250 | I15: =D15*G15 -> 400 | J15: N | K15: Not bought | M15: Foods the family already eats
A16: 1 - This week | B16: Cooking | C16: Butane stove (indoor-rated) | D16: 1 | E16: each | F16: 30 | G16: 50 | H16: =D16*F16 -> 30 | I16: =D16*G16 -> 50 | J16: N | K16: Not bought
A17: 1 - This week | B17: Cooking | C17: Butane canisters | D17: 12 | E17: each | F17: 2.5 | G17: 3.5 | H17: =D17*F17 -> 30 | I17: =D17*G17 -> 42 | J17: N | K17: Not bought | M17: First batch
A18: 1 - This week | B18: Cooking | C18: Manual can openers | D18: 2 | E18: each | F18: 8 | G18: 15 | H18: =D18*F18 -> 16 | I18: =D18*G18 -> 30 | J18: N | K18: Not bought
A19: 1 - This week | B19: Docs & Cash | C19: Cash reserve, small bills (set aside, not spent) | D19: 1 | E19: lot | F19: 0 | G19: 0 | H19: =D19*F19 -> 0 | I19: =D19*G19 -> 0 | J19: N | K19: Not bought | M19: $500-1,000 now, $1,000+ total
A20: 1 - This week | B20: Medical | C20: 90-day prescription refills | D20: 1 | E20: lot | F20: 0 | G20: 0 | H20: =D20*F20 -> 0 | I20: =D20*G20 -> 0 | J20: N | K20: Not bought | M20: Copays vary - not budgeted
A21: 2 - Within 2-4 weeks | B21: Heat & Power | C21: Dual-fuel inverter generator, 4,000-5,000 W running | D21: 1 | E21: each | F21: 1000 | G21: 1500 | H21: =D21*F21 -> 1000 | I21: =D21*G21 -> 1500 | J21: N | K21: Not bought | M21: Single most important purchase
A22: 2 - Within 2-4 weeks | B22: Heat & Power | C22: Generator inlet + interlock, installed with permit | D22: 1 | E22: job | F22: 600 | G22: 1500 | H22: =D22*F22 -> 600 | I22: =D22*G22 -> 1500 | J22: N | K22: Not bought | M22: Licensed electrician; ask about boiler transfer switch
A23: 2 - Within 2-4 weeks | B23: Heat & Power | C23: Generator power cord (matches inlet) | D23: 1 | E23: each | F23: 80 | G23: 150 | H23: =D23*F23 -> 80 | I23: =D23*G23 -> 150 | J23: N | K23: Not bought
A24: 2 - Within 2-4 weeks | B24: Heat & Power | C24: Generator tent/cover for snow | D24: 1 | E24: each | F24: 80 | G24: 200 | H24: =D24*F24 -> 80 | I24: =D24*G24 -> 200 | J24: N | K24: Not bought
A25: 2 - Within 2-4 weeks | B25: Heat & Power | C25: Generator chain + lock | D25: 1 | E25: each | F25: 30 | G25: 60 | H25: =D25*F25 -> 30 | I25: =D25*G25 -> 60 | J25: N | K25: Not bought
A26: 2 - Within 2-4 weeks | B26: Heat & Power | C26: 5-gal gasoline cans | D26: 4 | E26: each | F26: 30 | G26: 45 | H26: =D26*F26 -> 120 | I26: =D26*G26 -> 180 | J26: N | K26: Not bought
A27: 2 - Within 2-4 weeks | B27: Heat & Power | C27: Fuel stabilizer | D27: 1 | E27: bottle | F27: 15 | G27: 25 | H27: =D27*F27 -> 15 | I27: =D27*G27 -> 25 | J27: N | K27: Not bought
A28: 2 - Within 2-4 weeks | B28: Heat & Power | C28: Gasoline | D28: 20 | E28: gal | F28: 3.2 | G28: 3.8 | H28: =D28*F28 -> 64 | I28: =D28*G28 -> 76 | J28: N | K28: Not bought | M28: Check storage limits with Cumberland Fire
A29: 2 - Within 2-4 weeks | B29: Heat & Power | C29: 100-lb propane cylinders (empty) | D29: 3 | E29: each | F29: 150 | G29: 250 | H29: =D29*F29 -> 450 | I29: =D29*G29 -> 750 | J29: N | K29: Not bought | M29: Ask a local propane company
A30: 2 - Within 2-4 weeks | B30: Heat & Power | C30: 100-lb cylinder fills | D30: 3 | E30: fill | F30: 85 | G30: 130 | H30: =D30*F30 -> 255 | I30: =D30*G30 -> 390 | J30: N | K30: Not bought
A31: 2 - Within 2-4 weeks | B31: Heat & Power | C31: Propane hose/regulator for generator | D31: 1 | E31: each | F31: 40 | G31: 80 | H31: =D31*F31 -> 40 | I31: =D31*G31 -> 80 | J31: N | K31: Not bought
A32: 2 - Within 2-4 weeks | B32: Heat & Power | C32: 20-lb propane tanks (filled) | D32: 4 | E32: each | F32: 50 | G32: 65 | H32: =D32*F32 -> 200 | I32: =D32*G32 -> 260 | J32: N | K32: Not bought | M32: Shared with grill/camp stove
A33: 2 - Within 2-4 weeks | B33: Heat & Power | C33: Portable power station 1-2 kWh (LiFePO4) | D33: 1 | E33: each | F33: 600 | G33: 1100 | H33: =D33*F33 -> 600 | I33: =D33*G33 -> 1100 | J33: Y | K33: Not bought | M33: Quiet overnight power
A34: 2 - Within 2-4 weeks | B34: Heat & Power | C34: Folding solar panel 200-400 W | D34: 1 | E34: each | F34: 200 | G34: 400 | H34: =D34*F34 -> 200 | I34: =D34*G34 -> 400 | J34: Y | K34: Not bought | M34: Weak in RI winter
A35: 2 - Within 2-4 weeks | B35: Heat & Power | C35: Sleeping bags rated 0-20F | D35: 4 | E35: each | F35: 50 | G35: 100 | H35: =D35*F35 -> 200 | I35: =D35*G35 -> 400 | J35: N | K35: Not bought | M35: Winter-room fallback
A36: 2 - Within 2-4 weeks | B36: Heat & Power | C36: Window insulation film kits | D36: 2 | E36: kit | F36: 15 | G36: 25 | H36: =D36*F36 -> 30 | I36: =D36*G36 -> 50 | J36: N | K36: Not bought
A37: 2 - Within 2-4 weeks | B37: Water | C37: 55-gal food-grade water drums | D37: 6 | E37: each | F37: 50 | G37: 75 | H37: =D37*F37 -> 300 | I37: =D37*G37 -> 450 | J37: N | K37: Not bought | M37: 330 gal; place on basement slab
A38: 2 - Within 2-4 weeks | B38: Water | C38: Drum siphon pump + bung wrench | D38: 1 | E38: set | F38: 25 | G38: 40 | H38: =D38*F38 -> 25 | I38: =D38*G38 -> 40 | J38: N | K38: Not bought
A39: 2 - Within 2-4 weeks | B39: Water | C39: Gravity water filter (bacteria/protozoa) | D39: 1 | E39: each | F39: 150 | G39: 350 | H39: =D39*F39 -> 150 | I39: =D39*G39 -> 350 | J39: N | K39: Not bought
A40: 2 - Within 2-4 weeks | B40: Water | C40: Unscented bleach (fresh yearly) | D40: 1 | E40: jug | F40: 5 | G40: 8 | H40: =D40*F40 -> 5 | I40: =D40*G40 -> 8 | J40: N | K40: Not bought | M40: 8 drops/gal (6%) or 6 drops/gal (8.25%)
A41: 2 - Within 2-4 weeks | B41: Cooking | C41: Electric pressure cooker (skip if owned) | D41: 1 | E41: each | F41: 80 | G41: 120 | H41: =D41*F41 -> 80 | I41: =D41*G41 -> 120 | J41: Y | K41: Not bought | M41: Use during generator blocks
A42: 2 - Within 2-4 weeks | B42: Cooking | C42: Induction hot plate 1,800 W | D42: 1 | E42: each | F42: 60 | G42: 100 | H42: =D42*F42 -> 60 | I42: =D42*G42 -> 100 | J42: Y | K42: Not bought
A43: 2 - Within 2-4 weeks | B43: Comms | C43: GMRS handheld radios | D43: 4 | E43: each | F43: 30 | G43: 45 | H43: =D43*F43 -> 120 | I43: =D43*G43 -> 180 | J43: N | K43: Not bought
A44: 2 - Within 2-4 weeks | B44: Comms | C44: GMRS FCC license (covers family) | D44: 1 | E44: each | F44: 35 | G44: 35 | H44: =D44*F44 -> 35 | I44: =D44*G44 -> 35 | J44: N | K44: Not bought
A45: 3 - Within 60 days | B45: Food | C45: White rice | D45: 100 | E45: lb | F45: 0.7 | G45: 1 | H45: =D45*F45 -> 70 | I45: =D45*G45 -> 100 | J45: N | K45: Not bought | M45: ~165,000 kcal
A46: 3 - Within 60 days | B46: Food | C46: Rolled oats | D46: 50 | E46: lb | F46: 0.9 | G46: 1.4 | H46: =D46*F46 -> 45 | I46: =D46*G46 -> 70 | J46: N | K46: Not bought | M46: ~85,000 kcal
A47: 3 - Within 60 days | B47: Food | C47: Pasta | D47: 50 | E47: lb | F47: 1 | G47: 1.5 | H47: =D47*F47 -> 50 | I47: =D47*G47 -> 75 | J47: N | K47: Not bought | M47: ~80,000 kcal
A48: 3 - Within 60 days | B48: Food | C48: Lentils / split peas / dry beans | D48: 40 | E48: lb | F48: 1.2 | G48: 2 | H48: =D48*F48 -> 48 | I48: =D48*G48 -> 80 | J48: N | K48: Not bought | M48: ~60,000 kcal
A49: 3 - Within 60 days | B49: Food | C49: Cooking oil | D49: 3 | E49: gal | F49: 15 | G49: 25 | H49: =D49*F49 -> 45 | I49: =D49*G49 -> 75 | J49: N | K49: Not bought | M49: ~93,000 kcal
A50: 3 - Within 60 days | B50: Food | C50: Peanut butter, 16-oz jars | D50: 24 | E50: jar | F50: 2.5 | G50: 4 | H50: =D50*F50 -> 60 | I50: =D50*G50 -> 96 | J50: N | K50: Not bought | M50: ~65,000 kcal
A51: 3 - Within 60 days | B51: Food | C51: Sugar / honey | D51: 25 | E51: lb | F51: 0.8 | G51: 2 | H51: =D51*F51 -> 20 | I51: =D51*G51 -> 50 | J51: N | K51: Not bought | M51: ~44,000 kcal
A52: 3 - Within 60 days | B52: Food | C52: Flour / pancake mix | D52: 25 | E52: lb | F52: 0.6 | G52: 1 | H52: =D52*F52 -> 15 | I52: =D52*G52 -> 25 | J52: N | K52: Not bought | M52: ~41,000 kcal
A53: 3 - Within 60 days | B53: Food | C53: Nonfat powdered milk | D53: 25 | E53: lb | F53: 5 | G53: 9 | H53: =D53*F53 -> 125 | I53: =D53*G53 -> 225 | J53: N | K53: Not bought | M53: ~41,000 kcal
A54: 3 - Within 60 days | B54: Food | C54: Canned meat & fish | D54: 90 | E54: can | F54: 2.5 | G54: 4.5 | H54: =D54*F54 -> 225 | I54: =D54*G54 -> 405 | J54: N | K54: Not bought | M54: ~30,000 kcal
A55: 3 - Within 60 days | B55: Food | C55: Canned vegetables & fruit | D55: 180 | E55: can | F55: 1 | G55: 2 | H55: =D55*F55 -> 180 | I55: =D55*G55 -> 360 | J55: N | K55: Not bought | M55: ~45,000 kcal
A56: 3 - Within 60 days | B56: Food | C56: Canned soup / chili / stew | D56: 90 | E56: can | F56: 1.5 | G56: 3 | H56: =D56*F56 -> 135 | I56: =D56*G56 -> 270 | J56: N | K56: Not bought | M56: ~36,000 kcal
A57: 3 - Within 60 days | B57: Food | C57: Nuts, crackers, bars, trail mix | D57: 1 | E57: lot | F57: 250 | G57: 400 | H57: =D57*F57 -> 250 | I57: =D57*G57 -> 400 | J57: N | K57: Not bought | M57: ~80,000 kcal
A58: 3 - Within 60 days | B58: Food | C58: Coffee, tea, drink mixes, spices, vitamins | D58: 1 | E58: lot | F58: 100 | G58: 200 | H58: =D58*F58 -> 100 | I58: =D58*G58 -> 200 | J58: N | K58: Not bought
A59: 3 - Within 60 days | B59: Food | C59: 5-gal buckets + lids | D59: 10 | E59: each | F59: 8 | G59: 12 | H59: =D59*F59 -> 80 | I59: =D59*G59 -> 120 | J59: N | K59: Not bought | M59: For bulk storage
A60: 3 - Within 60 days | B60: Food | C60: Mylar bags + oxygen absorbers | D60: 1 | E60: kit | F60: 40 | G60: 60 | H60: =D60*F60 -> 40 | I60: =D60*G60 -> 60 | J60: N | K60: Not bought
A61: 3 - Within 60 days | B61: Cooking | C61: Butane canisters (second batch) | D61: 24 | E61: each | F61: 2.5 | G61: 3.5 | H61: =D61*F61 -> 60 | I61: =D61*G61 -> 84 | J61: N | K61: Not bought
A62: 3 - Within 60 days | B62: Medical | C62: Over-the-counter medicine stock | D62: 1 | E62: lot | F62: 100 | G62: 180 | H62: =D62*F62 -> 100 | I62: =D62*G62 -> 180 | J62: N | K62: Not bought
A63: 3 - Within 60 days | B63: Medical | C63: First-aid expansion (tourniquet, burns, splint) | D63: 1 | E63: lot | F63: 80 | G63: 150 | H63: =D63*F63 -> 80 | I63: =D63*G63 -> 150 | J63: N | K63: Not bought
A64: 3 - Within 60 days | B64: Medical | C64: Thermometers (2) + pulse oximeter | D64: 1 | E64: set | F64: 30 | G64: 50 | H64: =D64*F64 -> 30 | I64: =D64*G64 -> 50 | J64: N | K64: Not bought
A65: 3 - Within 60 days | B65: Medical | C65: Temporary dental filling kit | D65: 1 | E65: each | F65: 10 | G65: 15 | H65: =D65*F65 -> 10 | I65: =D65*G65 -> 15 | J65: N | K65: Not bought
A66: 3 - Within 60 days | B66: Medical | C66: Red Cross first aid/CPR class | D66: 4 | E66: person | F66: 70 | G66: 110 | H66: =D66*F66 -> 280 | I66: =D66*G66 -> 440 | J66: Y | K66: Not bought
A67: 3 - Within 60 days | B67: Hygiene | C67: Toilet paper | D67: 120 | E67: roll | F67: 0.6 | G67: 0.9 | H67: =D67*F67 -> 72 | I67: =D67*G67 -> 108 | J67: N | K67: Not bought
A68: 3 - Within 60 days | B68: Hygiene | C68: Wipes, sanitizer, soap, toiletries | D68: 1 | E68: lot | F68: 80 | G68: 140 | H68: =D68*F68 -> 80 | I68: =D68*G68 -> 140 | J68: N | K68: Not bought
A69: 3 - Within 60 days | B69: Hygiene | C69: Hand laundry washer, buckets, drying line | D69: 1 | E69: set | F69: 40 | G69: 70 | H69: =D69*F69 -> 40 | I69: =D69*G69 -> 70 | J69: N | K69: Not bought
A70: 3 - Within 60 days | B70: Sanitation | C70: Bucket toilet kits | D70: 2 | E70: each | F70: 25 | G70: 40 | H70: =D70*F70 -> 50 | I70: =D70*G70 -> 80 | J70: N | K70: Not bought
A71: 3 - Within 60 days | B71: Sanitation | C71: Contractor bags | D71: 1 | E71: box | F71: 25 | G71: 40 | H71: =D71*F71 -> 25 | I71: =D71*G71 -> 40 | J71: N | K71: Not bought
... A84: 3 - Within 60 days | B84: Morale | C84: Games, puzzles, books, journals | D84: 1 | E84: lot | F84: 75 | G84: 150 | H84: =D84*F84 -> 75 | I84: =D84*G84 -> 150 | J84: N | K84: Not bought
C85: TOTAL | H85: =SUM(H2:H84) -> 8906 | I85: =SUM(I2:I84) -> 15448 | L85: =SUM(L2:L84) -> 0

Sheet Maintenance
A1: Task | B1: Frequency | C1: Next due | D1: Done?
A2: Run generator 20 min under load; check oil | B2: Monthly | C2: 46357
A3: Test CO alarms and smoke alarms | B3: Monthly | C3: 46357
A4: Eat and replace a few stored food items | B4: Monthly | C4: 46357
A5: Recharge power station and power banks to ~80% | B5: Every 3 months | C5: 46419
A6: Check batteries, lanterns, radio | B6: Every 6 months (clock changes) | C6: 46460
A7: Rotate stabilized gasoline into cars; refill cans | B7: Every 12 months | C7: 46661
A8: Replace water in drums; buy fresh bleach | B8: Every 12 months | C8: 46661
A9: Check medicine and first-aid expiration dates | B9: Every 12 months | C9: 46661
A10: Boiler service + oil tank top-off before winter | B10: Every 12 months (Sept-Oct) | C10: 46645
A11: Refresh cash reserve; reprint contacts | B11: Every 12 months | C11: 46661

Sheet Generator Log
A1: Date | B1: Start | C1: Stop | D1: Hours | E1: Fuel | F1: Fuel added (gal or lb) | G1: Notes | I1: Total hours | J1: =SUM(D2:D101) -> 2
A2: 46336 | B2: 0.29166667 | C2: 0.375 | D2: =IF(AND(B2<>"",C2<>""),MOD(C2-B2,1)*24,"") -> 2 | E2: Gasoline | F2: 0 | G2: Example row - delete when you start logging | I2: Stored-fuel plan (hrs) | J2: 320 | K2: Approximate, from the plan doc
D3: =IF(AND(B3<>"",C3<>""),MOD(C3-B3,1)*24,"") | I3: Hours remaining | J3: =J2-J1 -> 318
D4: =IF(AND(B4<>"",C4<>""),MOD(C4-B4,1)*24,"")
D5: =IF(AND(B5<>"",C5<>""),MOD(C5-B5,1)*24,"")
D6: =IF(AND(B6<>"",C6<>""),MOD(C6-B6,1)*24,"")
D7: =IF(AND(B7<>"",C7<>""),MOD(C7-B7,1)*24,"")
D8: =IF(AND(B8<>"",C8<>""),MOD(C8-B8,1)*24,"")
D9: =IF(AND(B9<>"",C9<>""),MOD(C9-B9,1)*24,"")
D10: =IF(AND(B10<>"",C10<>""),MOD(C10-B10,1)*24,"")
D11: =IF(AND(B11<>"",C11<>""),MOD(C11-B11,1)*24,"")
D12: =IF(AND(B12<>"",C12<>""),MOD(C12-B12,1)*24,"")
D13: =IF(AND(B13<>"",C13<>""),MOD(C13-B13,1)*24,"")
D14: =IF(AND(B14<>"",C14<>""),MOD(C14-B14,1)*24,"")
D15: =IF(AND(B15<>"",C15<>""),MOD(C15-B15,1)*24,"")
... D101: =IF(AND(B101<>"",C101<>""),MOD(C101-B101,1)*24,"")
